gym3/__init__.py
gym3/asynchronous.py
gym3/asynchronous_test.py
gym3/concat.py
gym3/concat_test.py
gym3/env.py
gym3/extract_dict_ob.py
gym3/interactive.py
gym3/interop.py
gym3/interop_test.py
gym3/libenv.h
gym3/libenv.py
gym3/libenv_test.py
gym3/subproc.py
gym3/subproc_test.py
gym3/testing.py
gym3/testing_test.py
gym3/trajectory_recorder.py
gym3/trajectory_recorder_test.py
gym3/types.py
gym3/types_np.py
gym3/types_th.py
gym3/util.py
gym3/video_recorder.py
gym3/video_recorder_test.py
gym3/viewer.py
gym3/wrapper.py
gym3/wrappers.py
gym3/internal/__init__.py
gym3/internal/font.bin
gym3/internal/misc.py
gym3/internal/renderer.py
gym3/internal/test_with_mpi.py
gym3/scripts/__init__.py
gym3/scripts/random_agent.py
gym3-0.3.2.dist-info/DESCRIPTION.rst
gym3-0.3.2.dist-info/METADATA
gym3-0.3.2.dist-info/RECORD
gym3-0.3.2.dist-info/WHEEL
gym3-0.3.2.dist-info/metadata.json
gym3-0.3.2.dist-info/top_level.txt
